LICENSE
README.rst
setup.py
PyColorimetry/ColorimetricAnalysis.py
PyColorimetry/__init__.py
PyColorimetry.egg-info/PKG-INFO
PyColorimetry.egg-info/SOURCES.txt
PyColorimetry.egg-info/dependency_links.txt
PyColorimetry.egg-info/requires.txt
PyColorimetry.egg-info/top_level.txt