Metadata-Version: 2.1
Name: PyColorimetry
Version: 1.3.0
Summary: Python library for colorimetric analysis
Home-page: https://github.com/josorio398/PyColorimetry_Library
Download-URL: https://github.com/josorio398/PyColorimetry_Library/blob/main/PyColorimetry/ColorimetricAnalysis.py
Author: Prof. Jhonny Osorio Gallego, M.Sc.
Author-email: osoriojohnny1986@gmail.com
License: CC BY-NC-SA 4.0
Keywords: colorimetry,color analysis,image segmentation,SAM,GroundingDino,RGB,XYZ,CIELAB
Classifier: Development Status :: 4 - Beta
Classifier: Intended Audience :: Developers
Classifier: Topic :: Software Development :: Build Tools
Classifier: Programming Language :: Python :: 3.6
Classifier: Programming Language :: Python :: 3.7
Classifier: Programming Language :: Python :: 3.8
Classifier: Programming Language :: Python :: 3.9
License-File: LICENSE
